README.md
setup.py
bin/gwmp
gwmp/__init__.py
gwmp/gateway_message.py
gwmp/lorawan_message.py
gwmp/util.py
gwmp.egg-info/PKG-INFO
gwmp.egg-info/SOURCES.txt
gwmp.egg-info/dependency_links.txt
gwmp.egg-info/requires.txt
gwmp.egg-info/top_level.txt