Metadata-Version: 2.1
Name: gwmp
Version: 0.0.1
Summary: Parser for GWMP messages used in LoRa and LoRaWAN networks
Home-page: https://github.com/alesanfra/lora-gwmp
Author: Alessio Sanfratello
License: UNKNOWN
Platform: UNKNOWN
Classifier: Programming Language :: Python :: 3
Classifier: Operating System :: OS Independent
Classifier: Topic :: Scientific/Engineering :: Interface Engine/Protocol Translator
Classifier: Topic :: Software Development :: Libraries
Classifier: Topic :: Utilities
Classifier: Intended Audience :: Telecommunications Industry
Classifier: Intended Audience :: Science/Research
Requires-Python: >=3.6
